champ_dataset/__init__.py
champ_dataset/prompt.py
champ_dataset/dataset_files/v0.json
champ_dataset-1.0.0.dist-info/LICENSE
champ_dataset-1.0.0.dist-info/METADATA
champ_dataset-1.0.0.dist-info/WHEEL
champ_dataset-1.0.0.dist-info/top_level.txt
champ_dataset-1.0.0.dist-info/RECORD
